ech_datastructures/__init__.py
ech_datastructures/heap.py
ech_datastructures/tree_map.py
ech_datastructures-0.1.4.dist-info/LICENSE.txt
ech_datastructures-0.1.4.dist-info/METADATA
ech_datastructures-0.1.4.dist-info/WHEEL
ech_datastructures-0.1.4.dist-info/top_level.txt
ech_datastructures-0.1.4.dist-info/RECORD
