Metadata-Version: 2.1
Name: ech-datastructures
Version: 0.1.4
Summary: Comprehensive package of Python-native datastructures.
Home-page: https://github.com/rkechols/ech-datastructures
Author: Ryan Echols
Author-email: ryan@shadylakemedia.com
License: GNU GPL v3.0
Keywords: data structure structures datastructure datastructures tool tools util utils utility utilities
Classifier: Development Status :: 3 - Alpha
Classifier: Intended Audience :: Developers
Classifier: License :: OSI Approved :: GNU General Public License v3 (GPLv3)
Classifier: Programming Language :: Python :: 3.8
Classifier: Programming Language :: Python :: 3.9
Classifier: Programming Language :: Python :: 3.10
Classifier: Topic :: Software Development :: Libraries :: Python Modules
Classifier: Topic :: Utilities
Requires-Python: >=3.8
License-File: LICENSE.txt
